mapizy_property_analytics/__init__.py
mapizy_property_analytics/mapizy_property_analytics.py
mapizy_property_analytics-0.1.4.dist-info/LICENCE
mapizy_property_analytics-0.1.4.dist-info/METADATA
mapizy_property_analytics-0.1.4.dist-info/WHEEL
mapizy_property_analytics-0.1.4.dist-info/top_level.txt
mapizy_property_analytics-0.1.4.dist-info/RECORD
